llama_index/embeddings/langchain/__init__.py
llama_index/embeddings/langchain/base.py
llama_index_embeddings_langchain-0.4.0.dist-info/METADATA
llama_index_embeddings_langchain-0.4.0.dist-info/WHEEL
llama_index_embeddings_langchain-0.4.0.dist-info/licenses/LICENSE
llama_index_embeddings_langchain-0.4.0.dist-info/RECORD
